geotensor/__init__.py
geotensor/foo.py
geotensor-0.0.1.dist-info/LICENSE
geotensor-0.0.1.dist-info/METADATA
geotensor-0.0.1.dist-info/WHEEL
geotensor-0.0.1.dist-info/RECORD
